adafruit_circuitpython_pcf8563-2.0.7.dist-info/licenses/LICENSE
adafruit_pcf8563/clock.py
adafruit_pcf8563/pcf8563.py
adafruit_pcf8563/timer.py
adafruit_circuitpython_pcf8563-2.0.7.dist-info/METADATA
adafruit_circuitpython_pcf8563-2.0.7.dist-info/WHEEL
adafruit_circuitpython_pcf8563-2.0.7.dist-info/top_level.txt
adafruit_circuitpython_pcf8563-2.0.7.dist-info/RECORD
